cli.py
aiia_cli-2.5.3.dist-info/METADATA
aiia_cli-2.5.3.dist-info/WHEEL
aiia_cli-2.5.3.dist-info/entry_points.txt
aiia_cli-2.5.3.dist-info/top_level.txt
aiia_cli-2.5.3.dist-info/RECORD
