Metadata-Version: 2.4
Name: aiia-cli
Version: 2.5.3
Requires-Dist: click
Dynamic: requires-dist
